{
  "last-release-sha": "1443617116729e1a09131e2d31e6ba067acc23c8",
  "include-component-in-tag": true,
  "bump-minor-pre-major": true,
  "bump-patch-for-minor-pre-major": true,
  "plugins": [
    {
      "type": "linked-versions",
      "groupName": "pixel-io release",
      "components": ["components", "styles"]
    }
  ],
  "packages": {
    "packages/components": {
      "component": "components"
    },
    "packages/styles": {
      "component": "styles"
    },
    "packages/eslint-config": {},
    "packages/prettier-config": {}
  }
}
